{
    "$schema": "http://schema.management.azure.com/schemas/2015-01-01/deploymentTemplate.json#",
    "contentVersion": "1.0.0.0",
    "parameters": {
        "factoryName": {
            "type": "string",
            "metadata": "Data Factory name",
            "defaultValue": "EnterpriseDataSourceProdDF"
        }
    },
    "variables": {
        "factoryId": "[concat('Microsoft.DataFactory/factories/', parameters('factoryName'))]"
    },
    "resources": [
        {
            "name": "[concat(parameters('factoryName'), '/DS_ASQL_RewardsProgramDefaults')]",
            "type": "Microsoft.DataFactory/factories/datasets",
            "apiVersion": "2018-06-01",
            "properties": {
                "linkedServiceName": {
                    "referenceName": "RewardsDB",
                    "type": "LinkedServiceReference"
                },
                "folder": {
                    "name": "Rewards"
                },
                "annotations": [],
                "type": "AzureSqlTable",
                "schema": [
                    {
                        "name": "RewardsProgramDefaultId",
                        "type": "int",
                        "precision": 10
                    },
                    {
                        "name": "RewardsProgramURL",
                        "type": "varchar"
                    }
                ],
                "typeProperties": {
                    "schema": "dbo",
                    "table": "RewardsProgramDefaults"
                }
            },
            "dependsOn": []
        },
        {
            "name": "[concat(parameters('factoryName'), '/DS_ASQL_RewardsPrograms')]",
            "type": "Microsoft.DataFactory/factories/datasets",
            "apiVersion": "2018-06-01",
            "properties": {
                "linkedServiceName": {
                    "referenceName": "RewardsDB",
                    "type": "LinkedServiceReference"
                },
                "folder": {
                    "name": "Rewards"
                },
                "annotations": [],
                "type": "AzureSqlTable",
                "schema": [
                    {
                        "name": "RewardsProgramId",
                        "type": "int",
                        "precision": 10
                    },
                    {
                        "name": "RewardsConfigurationId",
                        "type": "int",
                        "precision": 10
                    },
                    {
                        "name": "RewardsProgramTypeId",
                        "type": "int",
                        "precision": 10
                    },
                    {
                        "name": "RewardsTypeId",
                        "type": "int",
                        "precision": 10
                    },
                    {
                        "name": "RewardsRoundingRuleId",
                        "type": "int",
                        "precision": 10
                    },
                    {
                        "name": "RewardsProgramURL",
                        "type": "varchar"
                    },
                    {
                        "name": "RewardsProgramExternalId",
                        "type": "varchar"
                    },
                    {
                        "name": "StartDate",
                        "type": "smalldatetime",
                        "precision": 16,
                        "scale": 0
                    },
                    {
                        "name": "EndDate",
                        "type": "smalldatetime",
                        "precision": 16,
                        "scale": 0
                    },
                    {
                        "name": "CreateDate",
                        "type": "datetime",
                        "precision": 23,
                        "scale": 3
                    },
                    {
                        "name": "CreateBy",
                        "type": "varchar"
                    },
                    {
                        "name": "ModifyDate",
                        "type": "datetime",
                        "precision": 23,
                        "scale": 3
                    },
                    {
                        "name": "ModifyBy",
                        "type": "varchar"
                    },
                    {
                        "name": "ProgramCode",
                        "type": "varchar"
                    }
                ],
                "typeProperties": {
                    "schema": "dbo",
                    "table": "RewardsPrograms"
                }
            },
            "dependsOn": []
        },
        {
            "name": "[concat(parameters('factoryName'), '/DS_ASQL_RewardsProgramTypes')]",
            "type": "Microsoft.DataFactory/factories/datasets",
            "apiVersion": "2018-06-01",
            "properties": {
                "linkedServiceName": {
                    "referenceName": "RewardsDB",
                    "type": "LinkedServiceReference"
                },
                "folder": {
                    "name": "Rewards"
                },
                "annotations": [],
                "type": "AzureSqlTable",
                "schema": [
                    {
                        "name": "RewardsProgramTypeId",
                        "type": "int",
                        "precision": 10
                    },
                    {
                        "name": "Name",
                        "type": "varchar"
                    },
                    {
                        "name": "Code",
                        "type": "varchar"
                    }
                ],
                "typeProperties": {
                    "schema": "dbo",
                    "table": "RewardsProgramTypes"
                }
            },
            "dependsOn": []
        },
        {
            "name": "[concat(parameters('factoryName'), '/DS_ASQL_RewardsRoundingRules')]",
            "type": "Microsoft.DataFactory/factories/datasets",
            "apiVersion": "2018-06-01",
            "properties": {
                "linkedServiceName": {
                    "referenceName": "RewardsDB",
                    "type": "LinkedServiceReference"
                },
                "folder": {
                    "name": "Rewards"
                },
                "annotations": [],
                "type": "AzureSqlTable",
                "schema": [
                    {
                        "name": "RewardsRoundingRuleId",
                        "type": "int",
                        "precision": 10
                    },
                    {
                        "name": "Name",
                        "type": "varchar"
                    },
                    {
                        "name": "Code",
                        "type": "varchar"
                    },
                    {
                        "name": "DefaultFg",
                        "type": "bit"
                    }
                ],
                "typeProperties": {
                    "schema": "dbo",
                    "table": "RewardsRoundingRules"
                }
            },
            "dependsOn": []
        },
        {
            "name": "[concat(parameters('factoryName'), '/DS_ASQL_RewardsTransactionTypes')]",
            "type": "Microsoft.DataFactory/factories/datasets",
            "apiVersion": "2018-06-01",
            "properties": {
                "linkedServiceName": {
                    "referenceName": "RewardsDB",
                    "type": "LinkedServiceReference"
                },
                "folder": {
                    "name": "Rewards"
                },
                "annotations": [],
                "type": "AzureSqlTable",
                "schema": [
                    {
                        "name": "RewardsTransactionTypeId",
                        "type": "int",
                        "precision": 10
                    },
                    {
                        "name": "RewardsProgramId",
                        "type": "int",
                        "precision": 10
                    },
                    {
                        "name": "TransactionTypeId",
                        "type": "int",
                        "precision": 10
                    }
                ],
                "typeProperties": {
                    "schema": "dbo",
                    "table": "RewardsTransactionTypes"
                }
            },
            "dependsOn": []
        },
        {
            "name": "[concat(parameters('factoryName'), '/DS_ASQL_RewardsTypes')]",
            "type": "Microsoft.DataFactory/factories/datasets",
            "apiVersion": "2018-06-01",
            "properties": {
                "linkedServiceName": {
                    "referenceName": "RewardsDB",
                    "type": "LinkedServiceReference"
                },
                "folder": {
                    "name": "Rewards"
                },
                "annotations": [],
                "type": "AzureSqlTable",
                "schema": [
                    {
                        "name": "RewardsTypeId",
                        "type": "int",
                        "precision": 10
                    },
                    {
                        "name": "Name",
                        "type": "varchar"
                    },
                    {
                        "name": "Code",
                        "type": "varchar"
                    }
                ],
                "typeProperties": {
                    "schema": "dbo",
                    "table": "RewardsTypes"
                }
            },
            "dependsOn": []
        },
        {
            "name": "[concat(parameters('factoryName'), '/DS_ASQL_TransactionTypes')]",
            "type": "Microsoft.DataFactory/factories/datasets",
            "apiVersion": "2018-06-01",
            "properties": {
                "linkedServiceName": {
                    "referenceName": "RewardsDB",
                    "type": "LinkedServiceReference"
                },
                "folder": {
                    "name": "Rewards"
                },
                "annotations": [],
                "type": "AzureSqlTable",
                "schema": [
                    {
                        "name": "TransactionTypeId",
                        "type": "int",
                        "precision": 10
                    },
                    {
                        "name": "AccountTypeId",
                        "type": "int",
                        "precision": 10
                    },
                    {
                        "name": "Name",
                        "type": "varchar"
                    },
                    {
                        "name": "Description",
                        "type": "varchar"
                    },
                    {
                        "name": "DefaultOption",
                        "type": "bit"
                    }
                ],
                "typeProperties": {
                    "schema": "dbo",
                    "table": "TransactionTypes"
                }
            },
            "dependsOn": []
        },
        {
            "name": "[concat(parameters('factoryName'), '/DS_SF_AccountTypes')]",
            "type": "Microsoft.DataFactory/factories/datasets",
            "apiVersion": "2018-06-01",
            "properties": {
                "linkedServiceName": {
                    "referenceName": "LS_SF_Application_DB",
                    "type": "LinkedServiceReference"
                },
                "folder": {
                    "name": "SnowFlake/Application_DB/Rewards"
                },
                "annotations": [],
                "type": "SnowflakeV2Table",
                "schema": [
                    {
                        "name": "ACCOUNTTYPEID",
                        "type": "NUMBER",
                        "precision": 38,
                        "scale": 0
                    },
                    {
                        "name": "NAME",
                        "type": "VARCHAR",
                        "precision": 100,
                        "scale": 0
                    },
                    {
                        "name": "DESCRIPTION",
                        "type": "VARCHAR",
                        "precision": 244,
                        "scale": 0
                    }
                ],
                "typeProperties": {
                    "schema": "REWARDS",
                    "table": "ACCOUNTTYPES"
                }
            },
            "dependsOn": []
        },
        {
            "name": "[concat(parameters('factoryName'), '/DS_SF_CashbackMethods')]",
            "type": "Microsoft.DataFactory/factories/datasets",
            "apiVersion": "2018-06-01",
            "properties": {
                "linkedServiceName": {
                    "referenceName": "LS_SF_Application_DB",
                    "type": "LinkedServiceReference"
                },
                "folder": {
                    "name": "SnowFlake/Application_DB/Rewards"
                },
                "annotations": [],
                "type": "SnowflakeV2Table",
                "schema": [
                    {
                        "name": "CASHBACKMETHODID",
                        "type": "NUMBER",
                        "precision": 38,
                        "scale": 0
                    },
                    {
                        "name": "NAME",
                        "type": "VARCHAR",
                        "precision": 100,
                        "scale": 0
                    },
                    {
                        "name": "DESCRIPTION",
                        "type": "VARCHAR",
                        "precision": 244,
                        "scale": 0
                    }
                ],
                "typeProperties": {
                    "schema": "REWARDS",
                    "table": "CASHBACKMETHODS"
                }
            },
            "dependsOn": []
        },
        {
            "name": "[concat(parameters('factoryName'), '/DS_SF_CashbackSourceAccountTypes')]",
            "type": "Microsoft.DataFactory/factories/datasets",
            "apiVersion": "2018-06-01",
            "properties": {
                "linkedServiceName": {
                    "referenceName": "LS_SF_Application_DB",
                    "type": "LinkedServiceReference"
                },
                "folder": {
                    "name": "SnowFlake/Application_DB/Rewards"
                },
                "annotations": [],
                "type": "SnowflakeV2Table",
                "schema": [
                    {
                        "name": "CASHBACKSOURCEACCOUNTTYPEID",
                        "type": "NUMBER",
                        "precision": 38,
                        "scale": 0
                    },
                    {
                        "name": "NAME",
                        "type": "VARCHAR",
                        "precision": 100,
                        "scale": 0
                    }
                ],
                "typeProperties": {
                    "schema": "REWARDS",
                    "table": "CASHBACKSOURCEACCOUNTTYPES"
                }
            },
            "dependsOn": []
        },
        {
            "name": "[concat(parameters('factoryName'), '/DS_SF_map_status')]",
            "type": "Microsoft.DataFactory/factories/datasets",
            "apiVersion": "2018-06-01",
            "properties": {
                "linkedServiceName": {
                    "referenceName": "LS_SF_Application_DB",
                    "type": "LinkedServiceReference"
                },
                "folder": {
                    "name": "SnowFlake/Application_DB/Rewards"
                },
                "annotations": [],
                "type": "SnowflakeV2Table",
                "schema": [
                    {
                        "name": "SOURCE_SYSTEM_KEY",
                        "type": "NUMBER",
                        "precision": 38,
                        "scale": 0
                    },
                    {
                        "name": "SOURCE_SYSTEM",
                        "type": "VARCHAR",
                        "precision": 10,
                        "scale": 0
                    },
                    {
                        "name": "EXTERNAL_STATUS_CODE",
                        "type": "VARCHAR",
                        "precision": 100,
                        "scale": 0
                    },
                    {
                        "name": "EXTERNAL_STATUS_CODE_DESC",
                        "type": "VARCHAR",
                        "precision": 100,
                        "scale": 0
                    },
                    {
                        "name": "INTERNAL_STATUS_CODE",
                        "type": "VARCHAR",
                        "precision": 100,
                        "scale": 0
                    },
                    {
                        "name": "INTERNAL_STATUS_CODE_DESC",
                        "type": "VARCHAR",
                        "precision": 100,
                        "scale": 0
                    },
                    {
                        "name": "REWARDS_STATUS_CODE",
                        "type": "VARCHAR",
                        "precision": 100,
                        "scale": 0
                    },
                    {
                        "name": "REWARDS_STATUS",
                        "type": "VARCHAR",
                        "precision": 100,
                        "scale": 0
                    },
                    {
                        "name": "REWARDS_STATUS_REASON_CODE",
                        "type": "VARCHAR",
                        "precision": 100,
                        "scale": 0
                    },
                    {
                        "name": "REWARDS_STATUS_REASON",
                        "type": "VARCHAR",
                        "precision": 100,
                        "scale": 0
                    },
                    {
                        "name": "EARN",
                        "type": "VARCHAR",
                        "precision": 100,
                        "scale": 0
                    },
                    {
                        "name": "REDEEM",
                        "type": "VARCHAR",
                        "precision": 100,
                        "scale": 0
                    },
                    {
                        "name": "POINTS_ARE_FORFEITED",
                        "type": "VARCHAR",
                        "precision": 100,
                        "scale": 0
                    },
                    {
                        "name": "LOAD_DATE",
                        "type": "DATE",
                        "precision": 10,
                        "scale": 0
                    },
                    {
                        "name": "LOAD_BY",
                        "type": "VARCHAR",
                        "precision": 20,
                        "scale": 0
                    }
                ],
                "typeProperties": {
                    "schema": "REWARDS",
                    "table": "MAP_STATUS"
                }
            },
            "dependsOn": []
        },
        {
            "name": "[concat(parameters('factoryName'), '/DS_SF_programSettings')]",
            "type": "Microsoft.DataFactory/factories/datasets",
            "apiVersion": "2018-06-01",
            "properties": {
                "linkedServiceName": {
                    "referenceName": "LS_SF_Application_DB",
                    "type": "LinkedServiceReference"
                },
                "folder": {
                    "name": "SnowFlake/Application_DB/Rewards"
                },
                "annotations": [],
                "type": "SnowflakeV2Table",
                "schema": [
                    {
                        "name": "PROGRAMSETTINGSID",
                        "type": "NUMBER",
                        "precision": 38,
                        "scale": 0
                    },
                    {
                        "name": "EXTERNALSETTINGID",
                        "type": "NUMBER",
                        "precision": 38,
                        "scale": 0
                    },
                    {
                        "name": "CREATEDATE",
                        "type": "TIMESTAMP_NTZ",
                        "precision": 29,
                        "scale": 9
                    },
                    {
                        "name": "MODIFYDATE",
                        "type": "TIMESTAMP_NTZ",
                        "precision": 29,
                        "scale": 9
                    }
                ],
                "typeProperties": {
                    "schema": "REWARDS",
                    "table": "PROGRAMSETTINGS"
                }
            },
            "dependsOn": []
        },
        {
            "name": "[concat(parameters('factoryName'), '/DS_SF_RewardsAdjustmentCode')]",
            "type": "Microsoft.DataFactory/factories/datasets",
            "apiVersion": "2018-06-01",
            "properties": {
                "linkedServiceName": {
                    "referenceName": "LS_SF_Application_DB",
                    "type": "LinkedServiceReference"
                },
                "folder": {
                    "name": "SnowFlake/Application_DB/Rewards"
                },
                "annotations": [],
                "type": "SnowflakeV2Table",
                "schema": [
                    {
                        "name": "ADJUSTMENTCODEID",
                        "type": "NUMBER",
                        "precision": 38,
                        "scale": 0
                    },
                    {
                        "name": "NAME",
                        "type": "VARCHAR",
                        "precision": 100,
                        "scale": 0
                    },
                    {
                        "name": "CODE",
                        "type": "VARCHAR",
                        "precision": 100,
                        "scale": 0
                    },
                    {
                        "name": "DESCRIPTION",
                        "type": "VARCHAR",
                        "scale": 0
                    }
                ],
                "typeProperties": {
                    "schema": "REWARDS",
                    "table": "REWARDSADJUSTMENTCODES"
                }
            },
            "dependsOn": []
        },
        {
            "name": "[concat(parameters('factoryName'), '/DS_SF_RewardsBonusCodes')]",
            "type": "Microsoft.DataFactory/factories/datasets",
            "apiVersion": "2018-06-01",
            "properties": {
                "linkedServiceName": {
                    "referenceName": "LS_SF_Application_DB",
                    "type": "LinkedServiceReference"
                },
                "folder": {
                    "name": "SnowFlake/Application_DB/Rewards"
                },
                "annotations": [],
                "type": "SnowflakeV2Table",
                "schema": [
                    {
                        "name": "BONUSCODEID",
                        "type": "NUMBER",
                        "precision": 38,
                        "scale": 0
                    },
                    {
                        "name": "NAME",
                        "type": "VARCHAR",
                        "precision": 100,
                        "scale": 0
                    },
                    {
                        "name": "CODE",
                        "type": "VARCHAR",
                        "precision": 100,
                        "scale": 0
                    },
                    {
                        "name": "DESCRIPTION",
                        "type": "VARCHAR",
                        "scale": 0
                    }
                ],
                "typeProperties": {
                    "schema": "REWARDS",
                    "table": "REWARDSBONUSCODES"
                }
            },
            "dependsOn": []
        },
        {
            "name": "[concat(parameters('factoryName'), '/DS_SF_RewardsProgramDefaults')]",
            "type": "Microsoft.DataFactory/factories/datasets",
            "apiVersion": "2018-06-01",
            "properties": {
                "linkedServiceName": {
                    "referenceName": "LS_SF_Application_DB",
                    "type": "LinkedServiceReference"
                },
                "folder": {
                    "name": "SnowFlake/Application_DB/Rewards"
                },
                "annotations": [],
                "type": "SnowflakeV2Table",
                "schema": [
                    {
                        "name": "REWARDSPROGRAMDEFAULTID",
                        "type": "NUMBER",
                        "precision": 38,
                        "scale": 0
                    },
                    {
                        "name": "REWARDSPROGRAMURL",
                        "type": "VARCHAR",
                        "scale": 0
                    }
                ],
                "typeProperties": {
                    "schema": "REWARDS",
                    "table": "REWARDSPROGRAMDEFAULTS"
                }
            },
            "dependsOn": []
        },
        {
            "name": "[concat(parameters('factoryName'), '/DS_SF_REWARDSPROGRAMS')]",
            "type": "Microsoft.DataFactory/factories/datasets",
            "apiVersion": "2018-06-01",
            "properties": {
                "linkedServiceName": {
                    "referenceName": "LS_SF_Application_DB",
                    "type": "LinkedServiceReference"
                },
                "folder": {
                    "name": "SnowFlake/Application_DB/Rewards"
                },
                "annotations": [],
                "type": "SnowflakeV2Table",
                "schema": [
                    {
                        "name": "REWARDSPROGRAMID",
                        "type": "NUMBER",
                        "precision": 38,
                        "scale": 0
                    },
                    {
                        "name": "REWARDSCONFIGURATIONID",
                        "type": "NUMBER",
                        "precision": 38,
                        "scale": 0
                    },
                    {
                        "name": "REWARDSPROGRAMTYPEID",
                        "type": "NUMBER",
                        "precision": 38,
                        "scale": 0
                    },
                    {
                        "name": "REWARDSTYPEID",
                        "type": "NUMBER",
                        "precision": 38,
                        "scale": 0
                    },
                    {
                        "name": "REWARDSROUNDINGRULEID",
                        "type": "NUMBER",
                        "precision": 38,
                        "scale": 0
                    },
                    {
                        "name": "REWARDSPROGRAMURL",
                        "type": "VARCHAR",
                        "scale": 0
                    },
                    {
                        "name": "REWARDSPROGRAMEXTERNALID",
                        "type": "VARCHAR",
                        "precision": 50,
                        "scale": 0
                    },
                    {
                        "name": "STARTDATE",
                        "type": "TIMESTAMP_NTZ",
                        "precision": 29,
                        "scale": 9
                    },
                    {
                        "name": "ENDDATE",
                        "type": "TIMESTAMP_NTZ",
                        "precision": 29,
                        "scale": 9
                    },
                    {
                        "name": "SRC_CREATEDATE",
                        "type": "TIMESTAMP_NTZ",
                        "precision": 29,
                        "scale": 9
                    },
                    {
                        "name": "CREATEBY",
                        "type": "VARCHAR",
                        "precision": 50,
                        "scale": 0
                    },
                    {
                        "name": "SRC_MODIFYDATE",
                        "type": "TIMESTAMP_NTZ",
                        "precision": 29,
                        "scale": 9
                    },
                    {
                        "name": "MODIFYBY",
                        "type": "VARCHAR",
                        "precision": 50,
                        "scale": 0
                    },
                    {
                        "name": "PROGRAMCODE",
                        "type": "VARCHAR",
                        "precision": 20,
                        "scale": 0
                    },
                    {
                        "name": "HASH_KEY",
                        "type": "VARCHAR",
                        "precision": 250,
                        "scale": 0
                    },
                    {
                        "name": "SOURCE_ID",
                        "type": "VARCHAR",
                        "scale": 0
                    },
                    {
                        "name": "LOAD_DATE",
                        "type": "DATE",
                        "precision": 10,
                        "scale": 0
                    },
                    {
                        "name": "BATCH_ID",
                        "type": "VARCHAR",
                        "precision": 250,
                        "scale": 0
                    },
                    {
                        "name": "LOAD_TYPE",
                        "type": "VARCHAR",
                        "precision": 50,
                        "scale": 0
                    },
                    {
                        "name": "CREATED_USER",
                        "type": "VARCHAR",
                        "precision": 250,
                        "scale": 0
                    },
                    {
                        "name": "UPDATED_USER",
                        "type": "VARCHAR",
                        "precision": 250,
                        "scale": 0
                    },
                    {
                        "name": "CREATE_DATE",
                        "type": "TIMESTAMP_NTZ",
                        "precision": 29,
                        "scale": 9
                    },
                    {
                        "name": "UPDATE_DATE",
                        "type": "TIMESTAMP_NTZ",
                        "precision": 29,
                        "scale": 9
                    }
                ],
                "typeProperties": {
                    "schema": "REWARDS",
                    "table": "REWARDSPROGRAMS"
                }
            },
            "dependsOn": []
        },
        {
            "name": "[concat(parameters('factoryName'), '/DS_SF_RewardsProgramTypes')]",
            "type": "Microsoft.DataFactory/factories/datasets",
            "apiVersion": "2018-06-01",
            "properties": {
                "linkedServiceName": {
                    "referenceName": "LS_SF_Application_DB",
                    "type": "LinkedServiceReference"
                },
                "folder": {
                    "name": "SnowFlake/Application_DB/Rewards"
                },
                "annotations": [],
                "type": "SnowflakeV2Table",
                "schema": [
                    {
                        "name": "REWARDSPROGRAMTYPEID",
                        "type": "NUMBER",
                        "precision": 38,
                        "scale": 0
                    },
                    {
                        "name": "NAME",
                        "type": "VARCHAR",
                        "precision": 100,
                        "scale": 0
                    },
                    {
                        "name": "CODE",
                        "type": "VARCHAR",
                        "precision": 8,
                        "scale": 0
                    },
                    {
                        "name": "HASH_KEY",
                        "type": "VARCHAR",
                        "precision": 250,
                        "scale": 0
                    },
                    {
                        "name": "SOURCE_ID",
                        "type": "VARCHAR",
                        "scale": 0
                    },
                    {
                        "name": "LOAD_DATE",
                        "type": "DATE",
                        "precision": 10,
                        "scale": 0
                    },
                    {
                        "name": "BATCH_ID",
                        "type": "VARCHAR",
                        "precision": 250,
                        "scale": 0
                    },
                    {
                        "name": "LOAD_TYPE",
                        "type": "VARCHAR",
                        "precision": 50,
                        "scale": 0
                    },
                    {
                        "name": "CREATED_USER",
                        "type": "VARCHAR",
                        "precision": 250,
                        "scale": 0
                    },
                    {
                        "name": "UPDATED_USER",
                        "type": "VARCHAR",
                        "precision": 250,
                        "scale": 0
                    },
                    {
                        "name": "CREATE_DATE",
                        "type": "TIMESTAMP_NTZ",
                        "precision": 29,
                        "scale": 9
                    },
                    {
                        "name": "UPDATE_DATE",
                        "type": "TIMESTAMP_NTZ",
                        "precision": 29,
                        "scale": 9
                    }
                ],
                "typeProperties": {
                    "schema": "REWARDS",
                    "table": "REWARDSPROGRAMTYPES"
                }
            },
            "dependsOn": []
        },
        {
            "name": "[concat(parameters('factoryName'), '/DS_SF_RewardsRoundingRules')]",
            "type": "Microsoft.DataFactory/factories/datasets",
            "apiVersion": "2018-06-01",
            "properties": {
                "linkedServiceName": {
                    "referenceName": "LS_SF_Application_DB",
                    "type": "LinkedServiceReference"
                },
                "folder": {
                    "name": "SnowFlake/Application_DB/Rewards"
                },
                "annotations": [],
                "type": "SnowflakeV2Table",
                "schema": [
                    {
                        "name": "REWARDSROUNDINGRULEID",
                        "type": "NUMBER",
                        "precision": 38,
                        "scale": 0
                    },
                    {
                        "name": "NAME",
                        "type": "VARCHAR",
                        "precision": 100,
                        "scale": 0
                    },
                    {
                        "name": "CODE",
                        "type": "VARCHAR",
                        "precision": 100,
                        "scale": 0
                    },
                    {
                        "name": "DEFAULTFG",
                        "type": "VARCHAR",
                        "precision": 1,
                        "scale": 0
                    }
                ],
                "typeProperties": {
                    "schema": "REWARDS",
                    "table": "REWARDSROUNDINGRULES"
                }
            },
            "dependsOn": []
        },
        {
            "name": "[concat(parameters('factoryName'), '/DS_SF_RewardsTransactionTypes')]",
            "type": "Microsoft.DataFactory/factories/datasets",
            "apiVersion": "2018-06-01",
            "properties": {
                "linkedServiceName": {
                    "referenceName": "LS_SF_Application_DB",
                    "type": "LinkedServiceReference"
                },
                "folder": {
                    "name": "SnowFlake/Application_DB/Rewards"
                },
                "annotations": [],
                "type": "SnowflakeV2Table",
                "schema": [
                    {
                        "name": "REWARDSTRANSACTIONTYPEID",
                        "type": "NUMBER",
                        "precision": 38,
                        "scale": 0
                    },
                    {
                        "name": "REWARDSPROGRAMID",
                        "type": "NUMBER",
                        "precision": 38,
                        "scale": 0
                    },
                    {
                        "name": "TRANSACTIONTYPEID",
                        "type": "NUMBER",
                        "precision": 38,
                        "scale": 0
                    }
                ],
                "typeProperties": {
                    "schema": "REWARDS",
                    "table": "REWARDSTRANSACTIONTYPES"
                }
            },
            "dependsOn": []
        },
        {
            "name": "[concat(parameters('factoryName'), '/DS_SF_RewardsTypes')]",
            "type": "Microsoft.DataFactory/factories/datasets",
            "apiVersion": "2018-06-01",
            "properties": {
                "linkedServiceName": {
                    "referenceName": "LS_SF_Application_DB",
                    "type": "LinkedServiceReference"
                },
                "folder": {
                    "name": "SnowFlake/Application_DB/Rewards"
                },
                "annotations": [],
                "type": "SnowflakeV2Table",
                "schema": [
                    {
                        "name": "REWARDSTYPEID",
                        "type": "NUMBER",
                        "precision": 38,
                        "scale": 0
                    },
                    {
                        "name": "NAME",
                        "type": "VARCHAR",
                        "precision": 100,
                        "scale": 0
                    },
                    {
                        "name": "CODE",
                        "type": "VARCHAR",
                        "precision": 100,
                        "scale": 0
                    }
                ],
                "typeProperties": {
                    "schema": "REWARDS",
                    "table": "REWARDSTYPES"
                }
            },
            "dependsOn": []
        }
    ]
}